magicpickle/__init__.py
magicpickle/magicpickle.py
magicpickle-0.0.6.dist-info/LICENSE
magicpickle-0.0.6.dist-info/METADATA
magicpickle-0.0.6.dist-info/WHEEL
magicpickle-0.0.6.dist-info/top_level.txt
magicpickle-0.0.6.dist-info/RECORD
