Metadata-Version: 2.2
Name: magicpickle
Version: 0.0.6
Summary: A wrapper around magic-wormhole and joblib to send pickled objects across the internet.
License: MIT License
Project-URL: Repository, https://github.com/jasonkena/magicpickle
License-File: LICENSE
Requires-Dist: joblib
Requires-Dist: magic-wormhole
